vivarium_build_utils/__init__.py
vivarium_build_utils/_version.py
vivarium_build_utils/resources.py
vivarium_build_utils/resources/makefiles/base.mk
vivarium_build_utils/resources/makefiles/test.mk
vivarium_build_utils/resources/scripts/install_dependency_branch.sh
vivarium_build_utils/resources/scripts/model_lineage.sh
vivarium_build_utils-2.1.1.dist-info/licenses/LICENSE.txt
vivarium_build_utils-2.1.1.dist-info/METADATA
vivarium_build_utils-2.1.1.dist-info/WHEEL
vivarium_build_utils-2.1.1.dist-info/top_level.txt
vivarium_build_utils-2.1.1.dist-info/RECORD
